{
   "topic" : [
      "language",
      "productivity"
   ],
   "perl_module" : "DDG::Spice::WordMap",
   "icon_url" : "/i/www.twinword.com.ico",
   "status" : "live",
   "name" : "WordMap",
   "example_query" : "similar to sound",
   "other_queries" : [
      "words like sound"
   ],
   "description" : "Generates semantically related words",
   "repo" : "spice",
   "src_name" : "Twinword",
   "id" : "word_map",
   "dev_milestone" : "live",
   "code" : [
      "lib/DDG/Spice/WordMap.pm",
      "t/WordMap.t"
   ]
}
